<screen>
  <text label="pays" name="country" default="France" validation="" required="true" errorMessage="" />
  <text label="ville" name="city" default="Paris" validation="" required="true" errorMessage="" />
  <select label="unité" name="unit" type="one" required="true">
    <option label="°C" key="C" checked="true"/>
    <option label="°F" key="F" checked="false"/>
  </select>
  <select label="langue" name="lang" type="multi" required="true">
    <option label="BR" key="br" checked="false"/>
    <option label="DE" key="de" checked="false"/>
    <option label="ES" key="es" checked="false"/>
    <option label="FR" key="fr" checked="true"/>
    <option label="IT" key="it" checked="false"/>
    <option label="JA" key="ja-JP" checked="false"/>
    <option label="UK" key="uk" checked="false"/>
    <option label="US" key="us" checked="false"/>
  </select>
</screen>
