<configapp><apiKey>&quot;6df32969-62fe-4011-bfac-d336ffa6ed6e&quot;</apiKey><version>&quot;1.1&quot;</version><name>&quot;Poubelles Reminder !&quot;</name><deployment>&quot;hosted&quot;</deployment><callback>&quot;&quot;</callback><author>&quot;Kamel Melka&quot;</author><access>&quot;button&quot;</access><access>&quot;ears&quot;</access><access>&quot;led&quot;</access><access>&quot;multimedia&quot;</access><configInstance><interruptible>false</interruptible><awake>false</awake><name>&quot;config&quot;</name><uuid>&quot;4a1379f4-881a-4aff-98e5-17d8cf6c8aad&quot;</uuid><params><key>&quot;awake&quot;</key><value>&quot;false&quot;</value></params><params><key>&quot;interruptible&quot;</key><value>&quot;false&quot;</value></params><params><key>&quot;permanentTriggerActivator&quot;</key><value>&quot;false&quot;</value></params><params><key>&quot;scheduledDateTriggerActivator&quot;</key><value>&quot;false&quot;</value></params><params><key>&quot;scheduledTriggerActivator&quot;</key><value>&quot;false&quot;</value></params></configInstance></configapp>