<configapp><apiKey>&quot;8654b86c-4d8d-411e-8eb2-35b263ea0f7c&quot;</apiKey><version>&quot;1.0.0&quot;</version><name>&quot;Haka&quot;</name><deployment>&quot;hosted&quot;</deployment><callback>&quot;&quot;</callback><author>&quot;Vincent P&quot;</author><access>&quot;button&quot;</access><access>&quot;ears&quot;</access><access>&quot;led&quot;</access><access>&quot;multimedia&quot;</access><configInstance><interruptible>false</interruptible><awake>false</awake><name>&quot;config&quot;</name><uuid>&quot;15c51b69-6128-4d3f-a047-3d2b1683b5d9&quot;</uuid><params><key>&quot;awake&quot;</key><value>&quot;false&quot;</value></params><params><key>&quot;interruptible&quot;</key><value>&quot;false&quot;</value></params><params><key>&quot;permanentTriggerActivator&quot;</key><value>&quot;false&quot;</value></params><params><key>&quot;scheduledDateTriggerActivator&quot;</key><value>&quot;false&quot;</value></params><params><key>&quot;scheduledTriggerActivator&quot;</key><value>&quot;false&quot;</value></params></configInstance></configapp>