<configapp><apiKey>&quot;afcb1502-fa08-41e1-abdb-bae29d7f530d&quot;</apiKey><version>&quot;1.0&quot;</version><name>&quot;Captain Tonio Volume 1&quot;</name><deployment>&quot;hosted&quot;</deployment><callback>&quot;&quot;</callback><author>&quot;Kamel Melka&quot;</author><access>&quot;button&quot;</access><access>&quot;http&quot;</access><access>&quot;multimedia&quot;</access><configInstance><interruptible>false</interruptible><awake>false</awake><name>&quot;config&quot;</name><uuid>&quot;2508604e-aaf4-4bb1-8e59-123cb6ce4743&quot;</uuid><params><key>&quot;awake&quot;</key><value>&quot;false&quot;</value></params><params><key>&quot;interruptible&quot;</key><value>&quot;false&quot;</value></params><params><key>&quot;permanentTriggerActivator&quot;</key><value>&quot;false&quot;</value></params><params><key>&quot;scheduledDateTriggerActivator&quot;</key><value>&quot;false&quot;</value></params><params><key>&quot;scheduledTriggerActivator&quot;</key><value>&quot;false&quot;</value></params></configInstance></configapp>