<configapp><apiKey>&quot;b2884a40-0b14-4838-9cf2-1d6bc9bd6469&quot;</apiKey><version>&quot;1.0&quot;</version><name>&quot;gaga&quot;</name><deployment>&quot;hosted&quot;</deployment><callback>&quot;&quot;</callback><author>&quot;Dev Wizz cc&quot;</author><access>&quot;button&quot;</access><access>&quot;led&quot;</access><access>&quot;multimedia&quot;</access><configInstance><interruptible>false</interruptible><awake>false</awake><name>&quot;config&quot;</name><uuid>&quot;d822d55b-b025-4c9c-b888-01c37c5f45e9&quot;</uuid><params><key>&quot;awake&quot;</key><value>&quot;false&quot;</value></params><params><key>&quot;interruptible&quot;</key><value>&quot;false&quot;</value></params><params><key>&quot;permanentTriggerActivator&quot;</key><value>&quot;false&quot;</value></params><params><key>&quot;scheduledDateTriggerActivator&quot;</key><value>&quot;false&quot;</value></params><params><key>&quot;scheduledTriggerActivator&quot;</key><value>&quot;false&quot;</value></params></configInstance></configapp>