<configapp><apiKey>&quot;f15a99b0-47c7-4673-957d-34fb02b89941&quot;</apiKey><version>&quot;1.0&quot;</version><name>&quot;M2 CLASSIC&quot;</name><deployment>&quot;hosted&quot;</deployment><callback>&quot;&quot;</callback><author>&quot;Kamel Melka&quot;</author><access>&quot;button&quot;</access><access>&quot;led&quot;</access><access>&quot;multimedia&quot;</access><configInstance><interruptible>false</interruptible><awake>false</awake><name>&quot;config&quot;</name><uuid>&quot;45b8635f-edc1-46de-8425-b4966dcf89d8&quot;</uuid><params><key>&quot;awake&quot;</key><value>&quot;false&quot;</value></params><params><key>&quot;duree&quot;</key><value>&quot;5&quot;</value></params><params><key>&quot;interruptible&quot;</key><value>&quot;false&quot;</value></params><params><key>&quot;permanentTriggerActivator&quot;</key><value>&quot;false&quot;</value></params><params><key>&quot;scheduledDateTriggerActivator&quot;</key><value>&quot;false&quot;</value></params><params><key>&quot;scheduledTriggerActivator&quot;</key><value>&quot;false&quot;</value></params></configInstance></configapp>